xpublish_intake/__init__.py
xpublish_intake/_version.py
xpublish_intake/plugins.py
xpublish_intake/__pycache__/__init__.cpython-310.pyc
xpublish_intake/__pycache__/plugins.cpython-310.pyc
xpublish_intake-1.0.0.dist-info/LICENSE.txt
xpublish_intake-1.0.0.dist-info/METADATA
xpublish_intake-1.0.0.dist-info/WHEEL
xpublish_intake-1.0.0.dist-info/entry_points.txt
xpublish_intake-1.0.0.dist-info/top_level.txt
xpublish_intake-1.0.0.dist-info/RECORD
