Metadata-Version: 2.1
Name: xpublish-intake
Version: 1.0.0
Summary: An xpublish plugin for serving intake catalogs
Author-email: Kyle Wilcox <kyle@axds.co>
Project-URL: Bug Tracker, https://github.com/axiom-data-science/xpublish-intake/issues
Project-URL: Homepage, https://github.com/axiom-data-science/xpublish-intake
Classifier: Environment :: Web Environment
Classifier: Intended Audience :: Developers
Classifier: License :: OSI Approved :: MIT License
Classifier: Operating System :: OS Independent
Classifier: Programming Language :: Python
Classifier: Programming Language :: Python :: 3
Classifier: Programming Language :: Python :: 3 :: Only
Classifier: Programming Language :: Python :: 3.8
Classifier: Programming Language :: Python :: 3.9
Classifier: Programming Language :: Python :: 3.10
Classifier: Programming Language :: Python :: 3.11
Classifier: Topic :: Internet :: WWW/HTTP
Classifier: Topic :: Internet :: WWW/HTTP :: Dynamic Content
Requires-Python: >=3.8
License-File: LICENSE.txt
Requires-Dist: xpublish
